dbtasks/__init__.py
dbtasks/admin.py
dbtasks/backend.py
dbtasks/contrib/__init__.py
dbtasks/contrib/mule.py
dbtasks/contrib/serve/__init__.py
dbtasks/contrib/serve/management/__init__.py
dbtasks/contrib/serve/management/commands/__init__.py
dbtasks/contrib/serve/management/commands/serve.py
dbtasks/defaults.py
dbtasks/management/__init__.py
dbtasks/management/commands/__init__.py
dbtasks/management/commands/taskrunner.py
dbtasks/migrations/0001_initial.py
dbtasks/migrations/0002_scheduledtask_delete_after.py
dbtasks/migrations/__init__.py
dbtasks/models.py
dbtasks/periodic.py
dbtasks/runner.py
dbtasks/schedule.py
dbtasks/testing.py
django_dbtasks-0.4.0.dist-info/WHEEL
django_dbtasks-0.4.0.dist-info/METADATA
django_dbtasks-0.4.0.dist-info/RECORD
