Metadata-Version: 2.3
Name: django-dbtasks
Version: 0.4.0
Summary: Database task backend and runner for Django tasks.
Author: Dan Watson
Author-email: Dan Watson <watsond@imsweb.com>
Classifier: Development Status :: 3 - Alpha
Classifier: Framework :: Django :: 6
Classifier: Intended Audience :: Developers
Classifier: License :: OSI Approved :: MIT License
Classifier: Programming Language :: Python
Classifier: Programming Language :: Python :: 3
Requires-Dist: granian[reload]>=2.4.2 ; extra == 'serve'
Requires-Python: >=3.12
Project-URL: Homepage, https://github.com/imsweb/django-dbtasks
Provides-Extra: serve
